subgroups/__init__.py
subgroups/exceptions.py
subgroups/algorithms/__init__.py
subgroups/algorithms/algorithm.py
subgroups/algorithms/subgroup_lists/__init__.py
subgroups/algorithms/subgroup_lists/dslm.py
subgroups/algorithms/subgroup_lists/gmsl.py
subgroups/algorithms/subgroup_lists/psld.py
subgroups/algorithms/subgroup_sets/__init__.py
subgroups/algorithms/subgroup_sets/bsd.py
subgroups/algorithms/subgroup_sets/cbsd.py
subgroups/algorithms/subgroup_sets/cpbsd.py
subgroups/algorithms/subgroup_sets/idsd.py
subgroups/algorithms/subgroup_sets/qfinder.py
subgroups/algorithms/subgroup_sets/sdiga.py
subgroups/algorithms/subgroup_sets/sdmap.py
subgroups/algorithms/subgroup_sets/sdmapstar.py
subgroups/algorithms/subgroup_sets/vlsd.py
subgroups/core/__init__.py
subgroups/core/operator.py
subgroups/core/pattern.py
subgroups/core/selector.py
subgroups/core/subgroup.py
subgroups/credibility_measures/__init__.py
subgroups/credibility_measures/credibility_measure.py
subgroups/credibility_measures/odds_ratio_glm.py
subgroups/credibility_measures/odds_ratio_stat.py
subgroups/credibility_measures/p_value_glm.py
subgroups/credibility_measures/p_value_independence.py
subgroups/credibility_measures/selector_contribution.py
subgroups/data_structures/__init__.py
subgroups/data_structures/bitset_bsd.py
subgroups/data_structures/bitset_qfinder.py
subgroups/data_structures/fp_tree_for_sdmap.py
subgroups/data_structures/fp_tree_for_sdmapstar.py
subgroups/data_structures/fp_tree_node.py
subgroups/data_structures/subgroup_list.py
subgroups/data_structures/vertical_list.py
subgroups/data_structures/vertical_list_with_bitsets.py
subgroups/data_structures/vertical_list_with_sets.py
subgroups/datasets/__init__.py
subgroups/datasets/csv/balloons.csv
subgroups/datasets/csv/car-evaluation.csv
subgroups/datasets/csv/covid-sp.csv
subgroups/datasets/csv/credit-g.csv
subgroups/datasets/csv/heart-disease.csv
subgroups/datasets/csv/income.csv
subgroups/datasets/csv/lenses.csv
subgroups-0.1.11.dist-info/licenses/LICENSE
subgroups-0.1.11.dist-info/METADATA
subgroups-0.1.11.dist-info/WHEEL
subgroups-0.1.11.dist-info/top_level.txt
subgroups-0.1.11.dist-info/RECORD
