Metadata-Version: 2.4
Name: subgroups
Version: 0.1.11
Summary: subgroups is a python library which contains a collection of subgroup discovery algorithms and other data analysis utilities.
Home-page: https://github.com/antoniolopezmc/subgroups
Author: Antonio López Martínez-Carrasco
Author-email: antoniolopezmc1995@gmail.com
Maintainer: Antonio López Martínez-Carrasco
Maintainer-email: antoniolopezmc1995@gmail.com
License: BSD-4-Clause
Keywords: python,data-science,machine-learning,data-analysis,subgroups,subgroup-discovery
Platform: any
Classifier: Programming Language :: Python :: 3
Classifier: Programming Language :: Python :: 3 :: Only
Classifier: Programming Language :: Python :: 3.11
Classifier: License :: OSI Approved :: BSD License
Classifier: Operating System :: OS Independent
Requires-Python: >=3.11.0
License-File: LICENSE
Requires-Dist: pandas>=2.1.4
Requires-Dist: bitarray>=3.0.0
Requires-Dist: statsmodels>=0.14.0
Dynamic: license-file
